quikcsv/__init__.py
quikcsv/decorator.py
quikcsv/exceptions.py
quikcsv/options.py
quikcsv/validation.py
tests/__init__.py
tests/test_decorator.py
tests/test_options.py
tests/test_validation.py
quikcsv-0.1.dist-info/LICENSE
quikcsv-0.1.dist-info/METADATA
quikcsv-0.1.dist-info/WHEEL
quikcsv-0.1.dist-info/top_level.txt
quikcsv-0.1.dist-info/RECORD
