Metadata-Version: 2.1
Name: quikcsv
Version: 0.1
Summary: Decorator for making quick mock csv files for testing.
Home-page: https://github.com/PRIV00/quikcsv
Author: Bryn Mck
License: UNKNOWN
Platform: UNKNOWN
